enumy/__init__.py
enumy/enum.py
enumy-1.0.2.dist-info/METADATA
enumy-1.0.2.dist-info/WHEEL
enumy-1.0.2.dist-info/top_level.txt
enumy-1.0.2.dist-info/RECORD
