Metadata-Version: 2.1
Name: enumy
Version: 1.0.2
Summary: Module to set predefined allowed values for a variable
Home-page: https://github.com/bytesentinel/enumy
Author: ByteSentinel
Author-email: info@bytesentinel.io
Classifier: Programming Language :: Python :: 3
Classifier: License :: OSI Approved :: MIT License
Classifier: Operating System :: OS Independent
Requires-Python: >=3.7
